quelfilm/__init__.py
quelfilm/app.py
quelfilm/engine.py
quelfilm/settings.py
resources/training.md
templates/index.html
quelfilm_chatbot_app-1.0.0.dist-info/entry_points.txt
quelfilm_chatbot_app-1.0.0.dist-info/LICENSE
quelfilm_chatbot_app-1.0.0.dist-info/WHEEL
quelfilm_chatbot_app-1.0.0.dist-info/METADATA
quelfilm_chatbot_app-1.0.0.dist-info/RECORD
