Metadata-Version: 2.1
Name: quelfilm-chatbot-app
Version: 1.0.0
Summary: webapp for choose a movie
Author: thomas.marquis.dev
Author-email: thomas.marquis.dev@gmail.com
Requires-Python: >=3.7,<4.0
Classifier: Programming Language :: Python :: 3
Classifier: Programming Language :: Python :: 3.7
Classifier: Programming Language :: Python :: 3.8
Requires-Dist: flask (>=1.1.1,<2.0.0)
Requires-Dist: nlp-tools-py-lib (==0.1.1)
